[
 {
  "en": "air-conditioning",
  "zh": "空调系统",
  "phonetic": "/ˈɛrkənˌdɪʃənɪŋ/",
  "example": "This is an air-conditioning.",
  "exampleZh": "这是一个空调系统。",
  "source": "template+generated",
  "word_id": "w2964"
 },
 {
  "en": "alarm clock",
  "zh": "闹钟",
  "phonetic": "/əˈlɑrm klɑk/",
  "example": "This is an alarm clock.",
  "exampleZh": "这是一个闹钟。",
  "source": "template+generated",
  "word_id": "w2965"
 },
 {
  "en": "armchair",
  "zh": "扶手椅",
  "phonetic": "/ˈɑrmˌʧɛr/",
  "example": "This is an armchair.",
  "exampleZh": "这是一个扶手椅。",
  "source": "template+generated",
  "word_id": "w2966"
 },
 {
  "en": "basement",
  "zh": "地下室",
  "phonetic": "/ˈbeɪsmənt/",
  "example": "This is a basement.",
  "exampleZh": "这是一个地下室。",
  "source": "template+generated",
  "word_id": "w2967"
 },
 {
  "en": "basin",
  "zh": "洗脸盆",
  "phonetic": "/ˈbeɪsən/",
  "example": "This is a basin.",
  "exampleZh": "这是一个洗脸盆。",
  "source": "template+generated",
  "word_id": "w2968"
 },
 {
  "en": "bath",
  "zh": "浴缸；洗澡",
  "phonetic": "/bæθ/",
  "example": "This is a bath.",
  "exampleZh": "这是一个浴缸；洗澡。",
  "source": "template+generated",
  "word_id": "w2969"
 },
 {
  "en": "blanket",
  "zh": "毯子；毛毯",
  "phonetic": "/ˈblæŋkɪt/",
  "example": "This is a blanket.",
  "exampleZh": "这是一个毯子；毛毯。",
  "source": "template+generated",
  "word_id": "w2970"
 },
 {
  "en": "bookcase",
  "zh": "书架",
  "phonetic": "/ˈbʊkˌkeɪs/",
  "example": "This is a bookcase.",
  "exampleZh": "这是一个书架。",
  "source": "template+generated",
  "word_id": "w2971"
 },
 {
  "en": "bowl",
  "zh": "碗",
  "phonetic": "/bəʊl/",
  "example": "I eat rice from a bowl.",
  "exampleZh": "我用碗吃饭。",
  "source": "reused",
  "word_id": "w2972"
 },
 {
  "en": "cabinet",
  "zh": "贮藏柜",
  "phonetic": "/ˈkæbənət/",
  "example": "This is a cabinet.",
  "exampleZh": "这是一个贮藏柜。",
  "source": "template+generated",
  "word_id": "w2973"
 },
 {
  "en": "carpet",
  "zh": "地毯",
  "phonetic": "/ˈkɑrpət/",
  "example": "This is a carpet.",
  "exampleZh": "这是一个地毯。",
  "source": "template+generated",
  "word_id": "w2974"
 },
 {
  "en": "CD",
  "zh": "光盘",
  "phonetic": "/ˈsiˈdi/",
  "example": "This is a CD.",
  "exampleZh": "这是一个光盘。",
  "source": "template+generated",
  "word_id": "w2975"
 },
 {
  "en": "CD player",
  "zh": "播放器",
  "phonetic": "/ˈsiˈdi pleɪər/",
  "example": "This is a CD player.",
  "exampleZh": "这是一个播放器。",
  "source": "template+generated",
  "word_id": "w2976"
 },
 {
  "en": "central heating",
  "zh": "中央暖气系统",
  "phonetic": "/ˈsɛntrəl ˈhitɪŋ/",
  "example": "This is a central heating.",
  "exampleZh": "这是一个中央暖气系统。",
  "source": "template+generated",
  "word_id": "w2977"
 },
 {
  "en": "chair",
  "zh": "椅子",
  "phonetic": "/tʃeə/",
  "example": "Sit on the chair.",
  "exampleZh": "坐在椅子上。",
  "source": "reused",
  "word_id": "w2978"
 },
 {
  "en": "chest of drawer",
  "zh": "抽屉柜",
  "phonetic": "/ʧɛst əv drɔr/",
  "example": "This is a chest of drawer.",
  "exampleZh": "这是一个抽屉柜。",
  "source": "template+generated",
  "word_id": "w2979"
 },
 {
  "en": "chimney",
  "zh": "烟囱",
  "phonetic": "/ˈʧɪmni/",
  "example": "This is a chimney.",
  "exampleZh": "这是一个烟囱。",
  "source": "template+generated",
  "word_id": "w2980"
 },
 {
  "en": "product",
  "zh": "清洁用品",
  "phonetic": "/ˈprɑdəkt/",
  "example": "This is a product.",
  "exampleZh": "这是一个清洁用品。",
  "source": "template+generated",
  "word_id": "w2981"
 },
 {
  "en": "closet",
  "zh": "壁橱",
  "phonetic": "/ˈklɑzət/",
  "example": "This is a closet.",
  "exampleZh": "这是一个壁橱。",
  "source": "template+generated",
  "word_id": "w2982"
 },
 {
  "en": "clothes line",
  "zh": "晒衣绳",
  "phonetic": "/kloʊðz laɪn/",
  "example": "This is a clothes line.",
  "exampleZh": "这是一个晒衣绳。",
  "source": "template+generated",
  "word_id": "w2983"
 },
 {
  "en": "computer",
  "zh": "电脑",
  "phonetic": "/kəmˈpjuːtə/",
  "example": "I use a computer.",
  "exampleZh": "我使用电脑。",
  "source": "reused",
  "word_id": "w2984"
 },
 {
  "en": "convenient",
  "zh": "方便的",
  "phonetic": "/kənˈvinjənt/",
  "example": "This is a convenient.",
  "exampleZh": "这是一个方便的。",
  "source": "template+generated",
  "word_id": "w2985"
 },
 {
  "en": "cooker",
  "zh": "炊具",
  "phonetic": "/ˈkʊkər/",
  "example": "This is a cooker.",
  "exampleZh": "这是一个炊具。",
  "source": "template+generated",
  "word_id": "w2986"
 },
 {
  "en": "curtain",
  "zh": "窗帘",
  "phonetic": "/ˈkərtən/",
  "example": "This is a curtain.",
  "exampleZh": "这是一个窗帘。",
  "source": "template+generated",
  "word_id": "w2987"
 },
 {
  "en": "dining room",
  "zh": "餐厅",
  "phonetic": "/ˈdaɪnɪŋ rum/",
  "example": "This is a dining room.",
  "exampleZh": "这是一个餐厅。",
  "source": "template+generated",
  "word_id": "w2988"
 },
 {
  "en": "downstairs",
  "zh": "往楼下，在楼下",
  "phonetic": "/ˈdaʊnˈstɛrz/",
  "example": "This is a downstairs.",
  "exampleZh": "这是一个往楼下，在楼下。",
  "source": "template+generated",
  "word_id": "w2989"
 },
 {
  "en": "drawer",
  "zh": "抽屉",
  "phonetic": "/drɔr/",
  "example": "This is a drawer.",
  "exampleZh": "这是一个抽屉。",
  "source": "template+generated",
  "word_id": "w2990"
 },
 {
  "en": "DVD",
  "zh": "光碟",
  "phonetic": "/ˌdiˌviˈdi/",
  "example": "This is a DVD.",
  "exampleZh": "这是一个光碟。",
  "source": "template+generated",
  "word_id": "w2991"
 },
 {
  "en": "DVD player",
  "zh": "影碟机",
  "phonetic": "/ˌdiˌviˈdi pleɪər/",
  "example": "This is a DVD player.",
  "exampleZh": "这是一个影碟机。",
  "source": "template+generated",
  "word_id": "w2992"
 },
 {
  "en": "entrance",
  "zh": "入口",
  "phonetic": "/ˈɛntrəns/",
  "example": "This is an entrance.",
  "exampleZh": "这是一个入口。",
  "source": "template+generated",
  "word_id": "w2993"
 },
 {
  "en": "frying pan",
  "zh": "煎锅",
  "phonetic": "/fraɪɪŋ pæn/",
  "example": "This is a frying pan.",
  "exampleZh": "这是一个煎锅。",
  "source": "template+generated",
  "word_id": "w2994"
 },
 {
  "en": "gate",
  "zh": "大门",
  "phonetic": "/ɡeɪt/",
  "example": "Go to gate 12.",
  "exampleZh": "去12号登机口。",
  "source": "reused",
  "word_id": "w2995"
 },
 {
  "en": "hall",
  "zh": "大厅；礼堂",
  "phonetic": "/hɔl/",
  "example": "This is a hall.",
  "exampleZh": "这是一个大厅；礼堂。",
  "source": "template+generated",
  "word_id": "w2996"
 },
 {
  "en": "heating",
  "zh": "供暖；暖气",
  "phonetic": "/ˈhitɪŋ/",
  "example": "This is a heating.",
  "exampleZh": "这是一个供暖；暖气。",
  "source": "template+generated",
  "word_id": "w2997"
 },
 {
  "en": "knife",
  "zh": "刀",
  "phonetic": "/naɪf/",
  "example": "Be careful with the knife.",
  "exampleZh": "小心刀。",
  "source": "reused",
  "word_id": "w2998"
 },
 {
  "en": "lawn",
  "zh": "草地",
  "phonetic": "/lɔn/",
  "example": "This is a lawn.",
  "exampleZh": "这是一个草地。",
  "source": "template+generated",
  "word_id": "w2999"
 },
 {
  "en": "microwave",
  "zh": "微波炉",
  "phonetic": "/ˈmaɪkrəˌweɪv/",
  "example": "This is a microwave.",
  "exampleZh": "这是一个微波炉。",
  "source": "template+generated",
  "word_id": "w3000"
 },
 {
  "en": "MP3 player",
  "zh": "播放器",
  "phonetic": "/ˌem piː ˈθriː ˈpleɪə/",
  "example": "This is a MP3 player.",
  "exampleZh": "这是一个播放器。",
  "source": "template+corrected",
  "word_id": "w3001"
 },
 {
  "en": "mug",
  "zh": "马克杯",
  "phonetic": "/məg/",
  "example": "This is a mug.",
  "exampleZh": "这是一个马克杯。",
  "source": "template+generated",
  "word_id": "w3002"
 },
 {
  "en": "neat",
  "zh": "整洁的",
  "phonetic": "/nit/",
  "example": "This is a neat.",
  "exampleZh": "这是一个整洁的。",
  "source": "template+generated",
  "word_id": "w3003"
 },
 {
  "en": "pillow",
  "zh": "枕头",
  "phonetic": "/ˈpɪloʊ/",
  "example": "This is a pillow.",
  "exampleZh": "这是一个枕头。",
  "source": "template+generated",
  "word_id": "w3004"
 },
 {
  "en": "radio",
  "zh": "收音机",
  "phonetic": "/ˈreɪdiˌoʊ/",
  "example": "This is a radio.",
  "exampleZh": "这是一个收音机。",
  "source": "template+generated",
  "word_id": "w3005"
 },
 {
  "en": "refrigerator",
  "zh": "电冰箱",
  "phonetic": "/rɪˈfrɪʤərˌeɪtər/",
  "example": "This is a refrigerator.",
  "exampleZh": "这是一个电冰箱。",
  "source": "template+generated",
  "word_id": "w3006"
 },
 {
  "en": "roof",
  "zh": "屋顶",
  "phonetic": "/rʊf/",
  "example": "This is a roof.",
  "exampleZh": "这是一个屋顶。",
  "source": "template+generated",
  "word_id": "w3007"
 },
 {
  "en": "sheet",
  "zh": "床单",
  "phonetic": "/ʃit/",
  "example": "This is a sheet.",
  "exampleZh": "这是一个床单。",
  "source": "template+generated",
  "word_id": "w3008"
 },
 {
  "en": "shelf",
  "zh": "架子；搁板",
  "phonetic": "/ʃɛlf/",
  "example": "This is a shelf.",
  "exampleZh": "这是一个架子；搁板。",
  "source": "template+generated",
  "word_id": "w3009"
 },
 {
  "en": "sink",
  "zh": "洗碗槽",
  "phonetic": "/sɪŋk/",
  "example": "This is a sink.",
  "exampleZh": "这是一个洗碗槽。",
  "source": "template+generated",
  "word_id": "w3010"
 },
 {
  "en": "sitting room",
  "zh": "起居室，客厅",
  "phonetic": "/ˈsɪtɪŋ rum/",
  "example": "This is a sitting room.",
  "exampleZh": "这是一个起居室，客厅。",
  "source": "template+generated",
  "word_id": "w3011"
 },
 {
  "en": "space",
  "zh": "空间",
  "phonetic": "/speɪs/",
  "example": "A rocket goes into space.",
  "exampleZh": "火箭飞向太空。",
  "source": "reused",
  "word_id": "w3012"
 },
 {
  "en": "tap",
  "zh": "水）龙头",
  "phonetic": "/tæp/",
  "example": "This is a tap.",
  "exampleZh": "这是一个水）龙头。",
  "source": "template+generated",
  "word_id": "w3013"
 },
 {
  "en": "toilet",
  "zh": "厕所",
  "phonetic": "/ˈtɔɪlət/",
  "example": "This is a toilet.",
  "exampleZh": "这是一个厕所。",
  "source": "template+generated",
  "word_id": "w3014"
 },
 {
  "en": "tool",
  "zh": "工具",
  "phonetic": "/tul/",
  "example": "This is a tool.",
  "exampleZh": "这是一个工具。",
  "source": "template+generated",
  "word_id": "w3015"
 },
 {
  "en": "toy",
  "zh": "玩具",
  "phonetic": "/tɔɪ/",
  "example": "This is a toy.",
  "exampleZh": "这是一个玩具。",
  "source": "template+generated",
  "word_id": "w3016"
 },
 {
  "en": "video recorder",
  "zh": "录像机",
  "phonetic": "/ˈvɪdioʊ rɪˈkɔrdər/",
  "example": "This is a video recorder.",
  "exampleZh": "这是一个录像机。",
  "source": "template+generated",
  "word_id": "w3017"
 },
 {
  "en": "machine",
  "zh": "洗衣机",
  "phonetic": "/məˈʃin/",
  "example": "This is a machine.",
  "exampleZh": "这是一个洗衣机。",
  "source": "template+generated",
  "word_id": "w3018"
 },
 {
  "en": "bar",
  "zh": "酒吧",
  "phonetic": "/bɑr/",
  "example": "This is a bar.",
  "exampleZh": "这是一个酒吧。",
  "source": "template+generated",
  "word_id": "w3019"
 },
 {
  "en": "beautiful",
  "zh": "美丽的",
  "phonetic": "/ˈbjutəfəl/",
  "example": "This is a beautiful.",
  "exampleZh": "这是一个美丽的。",
  "source": "template+generated",
  "word_id": "w3020"
 },
 {
  "en": "bookshop",
  "zh": "书店",
  "phonetic": "/ˈbʊkˌʃɑp/",
  "example": "This is a bookshop.",
  "exampleZh": "这是一个书店。",
  "source": "template+generated",
  "word_id": "w3021"
 },
 {
  "en": "boring",
  "zh": "无聊的",
  "phonetic": "/ˈbɔrɪŋ/",
  "example": "This is a boring.",
  "exampleZh": "这是一个无聊的。",
  "source": "template+generated",
  "word_id": "w3022"
 },
 {
  "en": "bus station",
  "zh": "公交车站",
  "phonetic": "/bəs ˈsteɪʃən/",
  "example": "This is a bus station.",
  "exampleZh": "这是一个公交车站。",
  "source": "template+generated",
  "word_id": "w3023"
 },
 {
  "en": "busy",
  "zh": "忙碌的",
  "phonetic": "/ˈbɪzi/",
  "example": "This is a busy.",
  "exampleZh": "这是一个忙碌的。",
  "source": "template+generated",
  "word_id": "w3024"
 },
 {
  "en": "city centre",
  "zh": "市中心",
  "phonetic": "/ˈsɪti ˈsɛntər/",
  "example": "This is a city centre.",
  "exampleZh": "这是一个市中心。",
  "source": "template+generated",
  "word_id": "w3025"
 },
 {
  "en": "coffee shop",
  "zh": "咖啡店",
  "phonetic": "/ˈkɔfi ʃɑp/",
  "example": "This is a coffee shop.",
  "exampleZh": "这是一个咖啡店。",
  "source": "template+generated",
  "word_id": "w3026"
 },
 {
  "en": "crowded",
  "zh": "拥挤的",
  "phonetic": "/ˈkraʊdɪd/",
  "example": "This is a crowded.",
  "exampleZh": "这是一个拥挤的。",
  "source": "template+generated",
  "word_id": "w3027"
 },
 {
  "en": "disco",
  "zh": "迪斯科舞厅",
  "phonetic": "/ˈdɪskoʊ/",
  "example": "This is a disco.",
  "exampleZh": "这是一个迪斯科舞厅。",
  "source": "template+generated",
  "word_id": "w3028"
 },
 {
  "en": "motorway",
  "zh": "高速公路",
  "phonetic": "/ˈməʊtəweɪ/",
  "example": "This is a motorway.",
  "exampleZh": "这是一个高速公路。",
  "source": "template+corrected",
  "word_id": "w3029"
 },
 {
  "en": "noise",
  "zh": "噪音",
  "phonetic": "/nɔɪz/",
  "example": "This is a noise.",
  "exampleZh": "这是一个噪音。",
  "source": "template+generated",
  "word_id": "w3030"
 },
 {
  "en": "palace",
  "zh": "宫殿",
  "phonetic": "/ˈpæləs/",
  "example": "This is a palace.",
  "exampleZh": "这是一个宫殿。",
  "source": "template+generated",
  "word_id": "w3031"
 },
 {
  "en": "park",
  "zh": "公园",
  "phonetic": "/pɑrk/",
  "example": "This is a park.",
  "exampleZh": "这是一个公园。",
  "source": "template+generated",
  "word_id": "w3032"
 },
 {
  "en": "railway station",
  "zh": "火车站",
  "phonetic": "/ˈreɪlˌweɪ ˈsteɪʃən/",
  "example": "This is a railway station.",
  "exampleZh": "这是一个火车站。",
  "source": "template+generated",
  "word_id": "w3033"
 },
 {
  "en": "roundabout",
  "zh": "环岛",
  "phonetic": "/ˈraʊndəbaʊt/",
  "example": "Turn left at the roundabout.",
  "exampleZh": "在环岛左转。",
  "source": "reused",
  "word_id": "w3034"
 },
 {
  "en": "square",
  "zh": "广场",
  "phonetic": "/skwɛr/",
  "example": "This is a square.",
  "exampleZh": "这是一个广场。",
  "source": "template+generated",
  "word_id": "w3035"
 },
 {
  "en": "street",
  "zh": "街道",
  "phonetic": "/strit/",
  "example": "This is a street.",
  "exampleZh": "这是一个街道。",
  "source": "template+generated",
  "word_id": "w3036"
 },
 {
  "en": "supermarket",
  "zh": "超市",
  "phonetic": "/ˈsuːpəmɑːkɪt/",
  "example": "I go to the supermarket.",
  "exampleZh": "我去超市。",
  "source": "reused",
  "word_id": "w3037"
 },
 {
  "en": "traffic lights",
  "zh": "交通信号灯",
  "phonetic": "/ˈtræfɪk laɪts/",
  "example": "This is a traffic lights.",
  "exampleZh": "这是一个交通信号灯。",
  "source": "template+generated",
  "word_id": "w3038"
 },
 {
  "en": "turning",
  "zh": "转弯处；岔路口",
  "phonetic": "/ˈtərnɪŋ/",
  "example": "This is a turning.",
  "exampleZh": "这是一个转弯处；岔路口。",
  "source": "template+generated",
  "word_id": "w3039"
 }
]