[
 {
  "en": "arrival",
  "zh": "到达",
  "phonetic": "/ərˈaɪvəl/",
  "example": "This is an arrival.",
  "exampleZh": "这是一个到达。",
  "source": "template+generated",
  "word_id": "w3491"
 },
 {
  "en": "by air",
  "zh": "乘飞机",
  "phonetic": "/baɪ ɛr/",
  "example": "This is a by air.",
  "exampleZh": "这是一个乘飞机。",
  "source": "template+generated",
  "word_id": "w3492"
 },
 {
  "en": "by land",
  "zh": "由陆路",
  "phonetic": "/baɪ lænd/",
  "example": "This is a by land.",
  "exampleZh": "这是一个由陆路。",
  "source": "template+generated",
  "word_id": "w3493"
 },
 {
  "en": "by rail",
  "zh": "乘火车；由铁路",
  "phonetic": "/baɪ reɪl/",
  "example": "This is a by rail.",
  "exampleZh": "这是一个乘火车；由铁路。",
  "source": "template+generated",
  "word_id": "w3494"
 },
 {
  "en": "by road",
  "zh": "由公路",
  "phonetic": "/baɪ roʊd/",
  "example": "This is a by road.",
  "exampleZh": "这是一个由公路。",
  "source": "template+generated",
  "word_id": "w3495"
 },
 {
  "en": "by sea",
  "zh": "乘船；走水路",
  "phonetic": "/baɪ si/",
  "example": "This is a by sea.",
  "exampleZh": "这是一个乘船；走水路。",
  "source": "template+generated",
  "word_id": "w3496"
 },
 {
  "en": "check-in",
  "zh": "登记；登记处",
  "phonetic": "/ˈtʃek ɪn/",
  "example": "This is a check-in.",
  "exampleZh": "这是一个登记；登记处。",
  "source": "template+corrected",
  "word_id": "w3497"
 },
 {
  "en": "comfortable",
  "zh": "舒服的",
  "phonetic": "/ˈkʌmftəbl/",
  "example": "The bed is comfortable.",
  "exampleZh": "床很舒适。",
  "source": "reused",
  "word_id": "w3498"
 },
 {
  "en": "convenient",
  "zh": "方便的，便利的",
  "phonetic": "/kənˈvinjənt/",
  "example": "This is a convenient.",
  "exampleZh": "这是一个方便的，便利的。",
  "source": "template+generated",
  "word_id": "w3499"
 },
 {
  "en": "crowded",
  "zh": "拥挤的",
  "phonetic": "/ˈkraʊdɪd/",
  "example": "This is a crowded.",
  "exampleZh": "这是一个拥挤的。",
  "source": "template+generated",
  "word_id": "w3500"
 },
 {
  "en": "dangerous",
  "zh": "危险的",
  "phonetic": "/ˈdeɪndʒərəs/",
  "example": "Be careful, it is dangerous.",
  "exampleZh": "小心，很危险。",
  "source": "reused",
  "word_id": "w3501"
 },
 {
  "en": "empty",
  "zh": "空的；空闲的",
  "phonetic": "/ˈɛmti/",
  "example": "This is an empty.",
  "exampleZh": "这是一个空的；空闲的。",
  "source": "template+generated",
  "word_id": "w3502"
 },
 {
  "en": "fare",
  "zh": "票价",
  "phonetic": "/fɛr/",
  "example": "This is a fare.",
  "exampleZh": "这是一个票价。",
  "source": "template+generated",
  "word_id": "w3503"
 },
 {
  "en": "land",
  "zh": "着陆",
  "phonetic": "/lænd/",
  "example": "This is a land.",
  "exampleZh": "这是一个着陆。",
  "source": "template+generated",
  "word_id": "w3504"
 },
 {
  "en": "leave",
  "zh": "离开",
  "phonetic": "/liv/",
  "example": "This is a leave.",
  "exampleZh": "这是一个离开。",
  "source": "template+generated",
  "word_id": "w3505"
 },
 {
  "en": "lounge",
  "zh": "休息室",
  "phonetic": "/laʊnʤ/",
  "example": "This is a lounge.",
  "exampleZh": "这是一个休息室。",
  "source": "template+generated",
  "word_id": "w3506"
 },
 {
  "en": "noisy",
  "zh": "吵闹的",
  "phonetic": "/ˈnɔɪzi/",
  "example": "The classroom is noisy.",
  "exampleZh": "教室很吵闹。",
  "source": "reused",
  "word_id": "w3507"
 },
 {
  "en": "quiet",
  "zh": "安静的",
  "phonetic": "/ˈkwaɪət/",
  "example": "The library is quiet.",
  "exampleZh": "图书馆很安静。",
  "source": "reused",
  "word_id": "w3508"
 },
 {
  "en": "safe",
  "zh": "安全的",
  "phonetic": "/seɪf/",
  "example": "This area is safe.",
  "exampleZh": "这个区域很安全。",
  "source": "reused",
  "word_id": "w3509"
 },
 {
  "en": "safety",
  "zh": "安全",
  "phonetic": "/ˈseɪfti/",
  "example": "This is a safety.",
  "exampleZh": "这是一个安全。",
  "source": "template+generated",
  "word_id": "w3510"
 },
 {
  "en": "tourist",
  "zh": "旅行者",
  "phonetic": "/ˈtʊərɪst/",
  "example": "There are many tourists.",
  "exampleZh": "有很多游客。",
  "source": "reused",
  "word_id": "w3511"
 },
 {
  "en": "traffic lights",
  "zh": "交通信号灯",
  "phonetic": "/ˈtræfɪk laɪts/",
  "example": "This is a traffic lights.",
  "exampleZh": "这是一个交通信号灯。",
  "source": "template+generated",
  "word_id": "w3512"
 },
 {
  "en": "visit",
  "zh": "访问；参观",
  "phonetic": "/ˈvɪzɪt/",
  "example": "This is a visit.",
  "exampleZh": "这是一个访问；参观。",
  "source": "template+generated",
  "word_id": "w3513"
 },
 {
  "en": "visitor",
  "zh": "来访者；参观者",
  "phonetic": "/ˈvɪzɪtər/",
  "example": "This is a visitor.",
  "exampleZh": "这是一个来访者；参观者。",
  "source": "template+generated",
  "word_id": "w3514"
 },
 {
  "en": "uncomfortable",
  "zh": "不舒服的",
  "phonetic": "/ənˈkəmfərtəbəl/",
  "example": "This is an uncomfortable.",
  "exampleZh": "这是一个不舒服的。",
  "source": "template+generated",
  "word_id": "w3515"
 },
 {
  "en": "waiting room",
  "zh": "候车室",
  "phonetic": "/ˈweɪtɪŋ rum/",
  "example": "This is a waiting room.",
  "exampleZh": "这是一个候车室。",
  "source": "template+generated",
  "word_id": "w3516"
 },
 {
  "en": "aeroplane",
  "zh": "飞机",
  "phonetic": "/ˈeərəpleɪn/",
  "example": "This is an aeroplane.",
  "exampleZh": "这是一个飞机。",
  "source": "template+corrected",
  "word_id": "w3517"
 },
 {
  "en": "bicycle bike",
  "zh": "自行车",
  "phonetic": "/ˈbaɪsɪkl baɪk/",
  "example": "This is a bicycle bike.",
  "exampleZh": "这是一个自行车。",
  "source": "template+corrected",
  "word_id": "w3518"
 },
 {
  "en": "cab",
  "zh": "出租车",
  "phonetic": "/kæb/",
  "example": "This is a cab.",
  "exampleZh": "这是一个出租车。",
  "source": "template+generated",
  "word_id": "w3519"
 },
 {
  "en": "coach",
  "zh": "长途汽车",
  "phonetic": "/koʊʧ/",
  "example": "This is a coach.",
  "exampleZh": "这是一个长途汽车。",
  "source": "template+generated",
  "word_id": "w3520"
 },
 {
  "en": "lorry",
  "zh": "卡车；货车",
  "phonetic": "/ˈlɔri/",
  "example": "This is a lorry.",
  "exampleZh": "这是一个卡车；货车。",
  "source": "template+generated",
  "word_id": "w3521"
 },
 {
  "en": "seatbelt",
  "zh": "安全带",
  "phonetic": "/ˈsitˌbɛlt/",
  "example": "This is a seatbelt.",
  "exampleZh": "这是一个安全带。",
  "source": "template+generated",
  "word_id": "w3522"
 },
 {
  "en": "ship",
  "zh": "轮船",
  "phonetic": "/ʃɪp/",
  "example": "This is a ship.",
  "exampleZh": "这是一个轮船。",
  "source": "template+generated",
  "word_id": "w3523"
 },
 {
  "en": "truck",
  "zh": "卡车",
  "phonetic": "/trək/",
  "example": "This is a truck.",
  "exampleZh": "这是一个卡车。",
  "source": "template+generated",
  "word_id": "w3524"
 },
 {
  "en": "wheel",
  "zh": "车轮；方向盘",
  "phonetic": "/wil/",
  "example": "This is a wheel.",
  "exampleZh": "这是一个车轮；方向盘。",
  "source": "template+generated",
  "word_id": "w3525"
 },
 {
  "en": "wing",
  "zh": "机翼",
  "phonetic": "/wɪŋ/",
  "example": "The bird has two wings.",
  "exampleZh": "鸟有两只翅膀。",
  "source": "reused",
  "word_id": "w3526"
 }
]